README.md
setup.py
enginehub/__init__.py
enginehub.sphinx_youtube.egg-info/PKG-INFO
enginehub.sphinx_youtube.egg-info/SOURCES.txt
enginehub.sphinx_youtube.egg-info/dependency_links.txt
enginehub.sphinx_youtube.egg-info/namespace_packages.txt
enginehub.sphinx_youtube.egg-info/requires.txt
enginehub.sphinx_youtube.egg-info/top_level.txt
enginehub/sphinx_youtube/__init__.py
enginehub/sphinx_youtube/youtube.py